miseqinteropreader/__init__.py
miseqinteropreader/__main__.py
miseqinteropreader/cli.py
miseqinteropreader/cli_utils.py
miseqinteropreader/error_metrics_parser.py
miseqinteropreader/interop_reader.py
miseqinteropreader/models.py
miseqinteropreader/py.typed
miseqinteropreader/read_records.py
miseqinteropreader/commands/__init__.py
miseqinteropreader/commands/extract.py
miseqinteropreader/commands/info.py
miseqinteropreader/commands/summary.py
miseqinteropreader/commands/validate.py
miseqinteropreader/formatters/__init__.py
miseqinteropreader/formatters/csv_formatter.py
miseqinteropreader/formatters/json_formatter.py
miseqinteropreader/formatters/table_formatter.py
miseqinteropreader-1.1.1.dist-info/METADATA
miseqinteropreader-1.1.1.dist-info/WHEEL
miseqinteropreader-1.1.1.dist-info/entry_points.txt
miseqinteropreader-1.1.1.dist-info/licenses/LICENSE
miseqinteropreader-1.1.1.dist-info/RECORD
