Metadata-Version: 2.4
Name: miseqinteropreader
Version: 1.1.1
Summary: Python parser for Illumina MiSeq InterOp binary files
Project-URL: Homepage, https://github.com/cfe-lab/miseqinteropreader
Project-URL: Repository, https://github.com/cfe-lab/miseqinteropreader
Project-URL: Issues, https://github.com/cfe-lab/miseqinteropreader/issues
Project-URL: Documentation, https://github.com/cfe-lab/miseqinteropreader#readme
Author-email: drickett <drickett@bccfe.ca>, Vitaliy Mysak <vmysak@bccfe.ca>
License: MIT
License-File: LICENSE
Keywords: binary-parser,bioinformatics,illumina,interop,miseq,sequencing
Classifier: Development Status :: 5 - Production/Stable
Classifier: Intended Audience :: Developers
Classifier: Intended Audience :: Science/Research
Classifier: License :: OSI Approved :: MIT License
Classifier: Operating System :: OS Independent
Classifier: Programming Language :: Python
Classifier: Programming Language :: Python :: 3
Classifier: Programming Language :: Python :: 3.11
Classifier: Programming Language :: Python :: 3.12
Classifier: Topic :: Scientific/Engineering :: Bio-Informatics
Classifier: Typing :: Typed
Requires-Python: <3.13,>=3.11
Requires-Dist: pandas<3.0.0,>=2.2.2
Requires-Dist: pyarrow>=16.0.0
Requires-Dist: pydantic<3.0.0,>=2.8.2
Provides-Extra: dev
Requires-Dist: codecov==2.1.13; extra == 'dev'
Requires-Dist: mypy-extensions>=1.0.0; extra == 'dev'
Requires-Dist: mypy>=1.10.1; extra == 'dev'
Requires-Dist: pandas-stubs>=2.2.2.240603; extra == 'dev'
Requires-Dist: pytest-cov>=5.0.0; extra == 'dev'
Requires-Dist: pytest-html>=4.1.1; extra == 'dev'
Requires-Dist: pytest>=8.2.2; extra == 'dev'
Requires-Dist: ruff>=0.5.1; extra == 'dev'
Requires-Dist: uv>=0.5.0; extra == 'dev'
